{
  "annotations": {
    "list": [
      {
        "builtIn": 1,
        "datasource": { "type": "grafana", "uid": "-- Grafana --" },
        "enable": true,
        "hide": true,
        "iconColor": "rgba(0, 211, 255, 1)",
        "name": "Annotations & Alerts",
        "type": "dashboard"
      }
    ]
  },
  "editable": true,
  "fiscalYearStartMonth": 0,
  "graphTooltip": 0,
  "links": [],
  "liveNow": false,
  "panels": [
    {
      "datasource": { "type": "prometheus", "uid": "Prometheus" },
      "fieldConfig": {
        "defaults": {
          "color": { "mode": "palette-classic" },
          "custom": {
            "axisCenteredZero": false,
            "axisColorMode": "text",
            "axisLabel": "",
            "axisPlacement": "auto",
            "barAlignment": 0,
            "drawStyle": "line",
            "fillOpacity": 10,
            "gradientMode": "none",
            "hideFrom": { "legend": false, "tooltip": false, "viz": false },
            "lineInterpolation": "linear",
            "lineWidth": 1,
            "pointSize": 5,
            "scaleDistribution": { "type": "linear" },
            "showPoints": "auto",
            "spanNulls": false,
            "stacking": { "group": "A", "mode": "none" },
            "thresholdsStyle": { "mode": "off" }
          },
          "mappings": [],
          "thresholds": {
            "mode": "absolute",
            "steps": [
              { "color": "green", "value": null },
              { "color": "red", "value": 80 }
            ]
          }
        },
        "overrides": []
      },
      "gridPos": { "h": 8, "w": 12, "x": 0, "y": 0 },
      "id": 1,
      "options": {
        "legend": { "calcs": [], "displayMode": "list", "placement": "bottom", "showLegend": true },
        "tooltip": { "mode": "single", "sort": "none" }
      },
      "targets": [
        {
          "datasource": { "type": "prometheus", "uid": "Prometheus" },
          "editorMode": "code",
          "expr": "sum(rate(ratelimit_requests_total[1m])) by (endpoint, result)",
          "legendFormat": "{{endpoint}} - {{result}}",
          "range": true,
          "refId": "A"
        }
      ],
      "title": "Requests per Second (by Endpoint & Result)",
      "type": "timeseries"
    },
    {
      "datasource": { "type": "prometheus", "uid": "Prometheus" },
      "fieldConfig": {
        "defaults": {
          "color": { "mode": "palette-classic" },
          "custom": {
            "axisCenteredZero": false,
            "axisColorMode": "text",
            "axisLabel": "",
            "axisPlacement": "auto",
            "barAlignment": 0,
            "drawStyle": "line",
            "fillOpacity": 10,
            "gradientMode": "none",
            "hideFrom": { "legend": false, "tooltip": false, "viz": false },
            "lineInterpolation": "linear",
            "lineWidth": 1,
            "pointSize": 5,
            "scaleDistribution": { "type": "linear" },
            "showPoints": "auto",
            "spanNulls": false,
            "stacking": { "group": "A", "mode": "none" },
            "thresholdsStyle": { "mode": "off" }
          },
          "mappings": [],
          "thresholds": {
            "mode": "absolute",
            "steps": [ { "color": "green", "value": null } ]
          },
          "unit": "s"
        },
        "overrides": []
      },
      "gridPos": { "h": 8, "w": 12, "x": 12, "y": 0 },
      "id": 2,
      "options": {
        "legend": { "calcs": [], "displayMode": "list", "placement": "bottom", "showLegend": true },
        "tooltip": { "mode": "single", "sort": "none" }
      },
      "targets": [
        {
          "datasource": { "type": "prometheus", "uid": "Prometheus" },
          "editorMode": "code",
          "expr": "histogram_quantile(0.95, sum(rate(ratelimit_redis_latency_seconds_bucket[1m])) by (le))",
          "legendFormat": "p95 Latency",
          "range": true,
          "refId": "A"
        },
        {
          "datasource": { "type": "prometheus", "uid": "Prometheus" },
          "editorMode": "code",
          "expr": "histogram_quantile(0.5, sum(rate(ratelimit_redis_latency_seconds_bucket[1m])) by (le))",
          "hide": false,
          "legendFormat": "p50 Latency",
          "range": true,
          "refId": "B"
        }
      ],
      "title": "Redis Latency (Quantiles)",
      "type": "timeseries"
    },
    {
      "datasource": { "type": "prometheus", "uid": "Prometheus" },
      "fieldConfig": {
        "defaults": {
          "color": { "mode": "thresholds" },
          "mappings": [
            {
              "options": {
                "0": { "color": "green", "index": 0, "text": "CLOSED" },
                "1": { "color": "red", "index": 1, "text": "OPEN" },
                "2": { "color": "orange", "index": 2, "text": "HALF_OPEN" }
              },
              "type": "value"
            }
          ],
          "thresholds": {
            "mode": "absolute",
            "steps": [
              { "color": "green", "value": null },
              { "color": "red", "value": 1 },
              { "color": "orange", "value": 2 }
            ]
          }
        },
        "overrides": []
      },
      "gridPos": { "h": 4, "w": 6, "x": 0, "y": 8 },
      "id": 3,
      "options": {
        "colorMode": "background",
        "graphMode": "none",
        "justifyMode": "auto",
        "orientation": "auto",
        "reduceOptions": { "calcs": ["lastNotNull"], "fields": "", "values": false },
        "textMode": "value"
      },
      "targets": [
        {
          "datasource": { "type": "prometheus", "uid": "Prometheus" },
          "editorMode": "code",
          "expr": "max(resilience4j_circuitbreaker_state{state=\"closed\"} * 0 or resilience4j_circuitbreaker_state{state=\"open\"} * 1 or resilience4j_circuitbreaker_state{state=\"half_open\"} * 2)",
          "legendFormat": "State",
          "range": true,
          "refId": "A"
        }
      ],
      "title": "Circuit Breaker Status",
      "type": "stat"
    },
    {
      "datasource": { "type": "prometheus", "uid": "Prometheus" },
      "fieldConfig": {
        "defaults": {
          "color": { "mode": "palette-classic" },
          "custom": {
            "axisCenteredZero": false,
            "axisColorMode": "text",
            "axisLabel": "",
            "axisPlacement": "auto",
            "barAlignment": 0,
            "drawStyle": "line",
            "fillOpacity": 10,
            "gradientMode": "none",
            "hideFrom": { "legend": false, "tooltip": false, "viz": false },
            "lineInterpolation": "linear",
            "lineWidth": 1,
            "pointSize": 5,
            "scaleDistribution": { "type": "linear" },
            "showPoints": "auto",
            "spanNulls": false,
            "stacking": { "group": "A", "mode": "none" },
            "thresholdsStyle": { "mode": "off" }
          },
          "mappings": [],
          "thresholds": {
            "mode": "absolute",
            "steps": [ { "color": "green", "value": null } ]
          }
        },
        "overrides": []
      },
      "gridPos": { "h": 4, "w": 18, "x": 6, "y": 8 },
      "id": 4,
      "options": {
        "legend": { "calcs": [], "displayMode": "list", "placement": "bottom", "showLegend": true },
        "tooltip": { "mode": "single", "sort": "none" }
      },
      "targets": [
        {
          "datasource": { "type": "prometheus", "uid": "Prometheus" },
          "editorMode": "code",
          "expr": "sum(rate(ratelimit_failopen_total[1m])) by (reason)",
          "legendFormat": "Fail-open ({{reason}})",
          "range": true,
          "refId": "A"
        }
      ],
      "title": "Fail-open Occurrences",
      "type": "timeseries"
    }
  ],
  "refresh": "5s",
  "schemaVersion": 36,
  "style": "dark",
  "tags": [ "ratelimit" ],
  "templating": { "list": [] },
  "time": { "from": "now-15m", "to": "now" },
  "timepicker": {},
  "timezone": "",
  "title": "Rate Limiter Dashboard",
  "uid": "ratelimit-dashboard",
  "version": 15,
  "weekStart": ""
}
